[
    {
        "timeline": {
            "edges": [
                {
                    "node": {
                        "__typename": "Commit"
                    }
                },
                {
                    "node": {
                        "__typename": "LabeledEvent"
                    }
                },
                {
                    "node": {
                        "__typename": "ReferencedEvent"
                    }
                },
                {
                    "node": {
                        "__typename": "MergedEvent"
                    }
                },
                {
                    "node": {
                        "__typename": "HeadRefDeletedEvent"
                    }
                },
                {
                    "node": {
                        "__typename": "ReferencedEvent"
                    }
                },
                {
                    "node": {
                        "__typename": "ReferencedEvent"
                    }
                }
            ]
        },
        "number": 1,
        "createdAt": "2019-06-10T02:29:52Z",
        "title": "Bump js-yaml from 3.12.2 to 3.13.1 in /packages/eslint-config-react-native-community",
        "bodyText": "Bumps js-yaml from 3.12.2 to 3.13.1.\n\nChangelog\nSourced from js-yaml's changelog.\n\n3.13.1 / 2019-04-05\n\nFix possible code execution in (already unsafe) .load(), #480.\n\n3.13.0 / 2019-03-20\n\nSecurity fix: safeLoad() can hang when arrays with nested refs\nused as key. Now throws exception for nested arrays. #475.\n\n\n\n\nCommits\n\n665aadd 3.13.1 released\nda8ecf2 Browser files rebuild\nb2f9e88 Merge pull request #480 from nodeca/toString\ne18afbf Fix possible code execution in (already unsafe) load()\n9d4ce5e 3.13.0 released\nf64c673 Browser files rebuild\na567ef3 Restrict data types for object keys\n59b6e76 Fix test name\nSee full diff in compare view\n\n\n\n\nDependabot will resolve any conflicts with this PR as long as you don't alter it yourself. You can also trigger a rebase manually by commenting @dependabot rebase.\n\n\nDependabot commands and options\n\nYou can trigger Dependabot actions by commenting on this PR:\n\n@dependabot rebase will rebase this PR\n@dependabot recreate will recreate this PR, overwriting any edits that have been made to it\n@dependabot merge will merge this PR after your CI passes on it\n@dependabot squash and merge will squash and merge this PR after your CI passes on it\n@dependabot cancel merge will cancel a previously requested merge and block automerging\n@dependabot reopen will reopen this PR if it is closed\n@dependabot ignore this [patch|minor|major] version will close this PR and stop Dependabot creating any more for this minor/major version (unless you reopen the PR or upgrade to it yourself)\n@dependabot ignore this dependency will close this PR and stop Dependabot creating any more for this dependency (unless you reopen the PR or upgrade to it yourself)\n@dependabot use these labels will set the current labels as the default for future PRs for this repo and language\n@dependabot use these reviewers will set the current reviewers as the default for future PRs for this repo and language\n@dependabot use these assignees will set the current assignees as the default for future PRs for this repo and language\n@dependabot use this milestone will set the current milestone as the default for future PRs for this repo and language",
        "state": "MERGED",
        "closed": true,
        "merged": true,
        "closedAt": "2019-06-16T19:28:36Z",
        "mergedBy": {
            "login": "dlowder-salesforce",
            "resourcePath": "/dlowder-salesforce"
        },
        "comments": {
            "nodes": []
        },
        "files": {
            "nodes": [
                {
                    "path": "packages/eslint-config-react-native-community/yarn.lock"
                }
            ]
        }
    },
    {
        "timeline": {
            "edges": [
                {
                    "node": {
                        "__typename": "Commit"
                    }
                },
                {
                    "node": {
                        "__typename": "LabeledEvent"
                    }
                },
                {
                    "node": {
                        "__typename": "PullRequestReview"
                    }
                },
                {
                    "node": {
                        "__typename": "ReferencedEvent"
                    }
                },
                {
                    "node": {
                        "__typename": "MergedEvent"
                    }
                },
                {
                    "node": {
                        "__typename": "HeadRefDeletedEvent"
                    }
                }
            ]
        },
        "number": 35,
        "createdAt": "2019-12-28T04:19:53Z",
        "title": "Bump handlebars from 4.1.0 to 4.5.3",
        "bodyText": "Bumps handlebars from 4.1.0 to 4.5.3.\n\nChangelog\nSourced from handlebars's changelog.\n\nv4.5.3 - November 18th, 2019\nBugfixes:\n\nfix: add \"no-prototype-builtins\" eslint-rule and fix all occurences - f7f05d7\nfix: add more properties required to be enumerable - 1988878\n\nChores / Build:\n\nfix: use !== 0 instead of != 0 - c02b05f\nadd chai and dirty-chai and sinon, for cleaner test-assertions and spies,\ndeprecate old assertion-methods  - 93e284e, 886ba86, 0817dad, 93516a0\n\nSecurity:\n\nThe properties __proto__, __defineGetter__, __defineSetter__ and __lookupGetter__\nhave been added to the list of \"properties that must be enumerable\".\nIf a property by that name is found and not enumerable on its parent,\nit will silently evaluate to undefined. This is done in both the compiled template and the \"lookup\"-helper.\nThis will prevent new Remote-Code-Execution exploits that have been\npublished recently.\n\nCompatibility notes:\n\nDue to the security-fixes. The semantics of the templates using\n__proto__, __defineGetter__, __defineSetter__ and __lookupGetter__ in the respect that those expression now return\nundefined rather than their actual value from the proto.\nThe semantics have not changed in cases where the properties are  enumerable, as in:\n\n{\n  __proto__: 'some string'\n}\n\nThe change may be breaking in that respect, but we still only\nincrease the patch-version, because the incompatible use-cases\nare not intended, undocumented and far less important than fixing\nRemote-Code-Execution exploits on existing systems.\n\nCommits\nv4.5.2 - November 13th, 2019\nBugfixes\n\nfix: use String(field) in lookup when checking for \"constructor\" - d541378\ntest: add fluent API for testing Handlebars - c2ac79c\n\nCompatibility notes:\n\nno incompatibility are to be expected\n\n ... (truncated)\n\n\n\nCommits\n\nc819c8b v4.5.3\n827c9d0 Update release notes\nf7f05d7 fix: add \"no-prototype-builtins\" eslint-rule and fix all occurences\n1988878 fix: add more properties required to be enumerable\n886ba86 test/chore: add chai/expect and sinon to \"runtime\"-environment\n0817dad test: add sinon as global variable to eslint in the specs\n93516a0 test: add sinon.js for spies, deprecate current assertions\n93e284e chore: add chai and dirty-chai for better test assertions\nc02b05f fix: use !== 0 instead of != 0\n8de121d v4.5.2\nAdditional commits viewable in compare view\n\n\n\n\nDependabot will resolve any conflicts with this PR as long as you don't alter it yourself. You can also trigger a rebase manually by commenting @dependabot rebase.\n\n\nDependabot commands and options\n\nYou can trigger Dependabot actions by commenting on this PR:\n\n@dependabot rebase will rebase this PR\n@dependabot recreate will recreate this PR, overwriting any edits that have been made to it\n@dependabot merge will merge this PR after your CI passes on it\n@dependabot squash and merge will squash and merge this PR after your CI passes on it\n@dependabot cancel merge will cancel a previously requested merge and block automerging\n@dependabot reopen will reopen this PR if it is closed\n@dependabot ignore this [patch|minor|major] version will close this PR and stop Dependabot creating any more for this minor/major version (unless you reopen the PR or upgrade to it yourself)\n@dependabot ignore this dependency will close this PR and stop Dependabot creating any more for this dependency (unless you reopen the PR or upgrade to it yourself)\n@dependabot use these labels will set the current labels as the default for future PRs for this repo and language\n@dependabot use these reviewers will set the current reviewers as the default for future PRs for this repo and language\n@dependabot use these assignees will set the current assignees as the default for future PRs for this repo and language\n@dependabot use this milestone will set the current milestone as the default for future PRs for this repo and language\n\nYou can disable automated security fix PRs for this repo from the Security Alerts page.",
        "state": "MERGED",
        "closed": true,
        "merged": true,
        "closedAt": "2020-04-06T18:14:46Z",
        "mergedBy": {
            "login": "dlowder-salesforce",
            "resourcePath": "/dlowder-salesforce"
        },
        "comments": {
            "nodes": []
        },
        "files": {
            "nodes": [
                {
                    "path": "yarn.lock"
                }
            ]
        }
    },
    {
        "timeline": {
            "edges": [
                {
                    "node": {
                        "__typename": "Commit"
                    }
                },
                {
                    "node": {
                        "__typename": "LabeledEvent"
                    }
                },
                {
                    "node": {
                        "__typename": "PullRequestReview"
                    }
                },
                {
                    "node": {
                        "__typename": "ReferencedEvent"
                    }
                },
                {
                    "node": {
                        "__typename": "MergedEvent"
                    }
                },
                {
                    "node": {
                        "__typename": "HeadRefDeletedEvent"
                    }
                }
            ]
        },
        "number": 36,
        "createdAt": "2019-12-29T17:02:18Z",
        "title": "Bump handlebars from 4.0.11 to 4.5.3 in /ReactCommon/hermes/inspector/tools/msggen",
        "bodyText": "Bumps handlebars from 4.0.11 to 4.5.3.\n\nChangelog\nSourced from handlebars's changelog.\n\nv4.5.3 - November 18th, 2019\nBugfixes:\n\nfix: add \"no-prototype-builtins\" eslint-rule and fix all occurences - f7f05d7\nfix: add more properties required to be enumerable - 1988878\n\nChores / Build:\n\nfix: use !== 0 instead of != 0 - c02b05f\nadd chai and dirty-chai and sinon, for cleaner test-assertions and spies,\ndeprecate old assertion-methods  - 93e284e, 886ba86, 0817dad, 93516a0\n\nSecurity:\n\nThe properties __proto__, __defineGetter__, __defineSetter__ and __lookupGetter__\nhave been added to the list of \"properties that must be enumerable\".\nIf a property by that name is found and not enumerable on its parent,\nit will silently evaluate to undefined. This is done in both the compiled template and the \"lookup\"-helper.\nThis will prevent new Remote-Code-Execution exploits that have been\npublished recently.\n\nCompatibility notes:\n\nDue to the security-fixes. The semantics of the templates using\n__proto__, __defineGetter__, __defineSetter__ and __lookupGetter__ in the respect that those expression now return\nundefined rather than their actual value from the proto.\nThe semantics have not changed in cases where the properties are  enumerable, as in:\n\n{\n  __proto__: 'some string'\n}\n\nThe change may be breaking in that respect, but we still only\nincrease the patch-version, because the incompatible use-cases\nare not intended, undocumented and far less important than fixing\nRemote-Code-Execution exploits on existing systems.\n\nCommits\nv4.5.2 - November 13th, 2019\nBugfixes\n\nfix: use String(field) in lookup when checking for \"constructor\" - d541378\ntest: add fluent API for testing Handlebars - c2ac79c\n\nCompatibility notes:\n\nno incompatibility are to be expected\n\n ... (truncated)\n\n\n\nCommits\n\nc819c8b v4.5.3\n827c9d0 Update release notes\nf7f05d7 fix: add \"no-prototype-builtins\" eslint-rule and fix all occurences\n1988878 fix: add more properties required to be enumerable\n886ba86 test/chore: add chai/expect and sinon to \"runtime\"-environment\n0817dad test: add sinon as global variable to eslint in the specs\n93516a0 test: add sinon.js for spies, deprecate current assertions\n93e284e chore: add chai and dirty-chai for better test assertions\nc02b05f fix: use !== 0 instead of != 0\n8de121d v4.5.2\nAdditional commits viewable in compare view\n\n\n\n\nDependabot will resolve any conflicts with this PR as long as you don't alter it yourself. You can also trigger a rebase manually by commenting @dependabot rebase.\n\n\nDependabot commands and options\n\nYou can trigger Dependabot actions by commenting on this PR:\n\n@dependabot rebase will rebase this PR\n@dependabot recreate will recreate this PR, overwriting any edits that have been made to it\n@dependabot merge will merge this PR after your CI passes on it\n@dependabot squash and merge will squash and merge this PR after your CI passes on it\n@dependabot cancel merge will cancel a previously requested merge and block automerging\n@dependabot reopen will reopen this PR if it is closed\n@dependabot ignore this [patch|minor|major] version will close this PR and stop Dependabot creating any more for this minor/major version (unless you reopen the PR or upgrade to it yourself)\n@dependabot ignore this dependency will close this PR and stop Dependabot creating any more for this dependency (unless you reopen the PR or upgrade to it yourself)\n@dependabot use these labels will set the current labels as the default for future PRs for this repo and language\n@dependabot use these reviewers will set the current reviewers as the default for future PRs for this repo and language\n@dependabot use these assignees will set the current assignees as the default for future PRs for this repo and language\n@dependabot use this milestone will set the current milestone as the default for future PRs for this repo and language\n\nYou can disable automated security fix PRs for this repo from the Security Alerts page.",
        "state": "MERGED",
        "closed": true,
        "merged": true,
        "closedAt": "2020-04-06T18:14:23Z",
        "mergedBy": {
            "login": "dlowder-salesforce",
            "resourcePath": "/dlowder-salesforce"
        },
        "comments": {
            "nodes": []
        },
        "files": {
            "nodes": [
                {
                    "path": "ReactCommon/hermes/inspector/tools/msggen/yarn.lock"
                }
            ]
        }
    },
    {
        "timeline": {
            "edges": [
                {
                    "node": {
                        "__typename": "Commit"
                    }
                },
                {
                    "node": {
                        "__typename": "LabeledEvent"
                    }
                },
                {
                    "node": {
                        "__typename": "PullRequestReview"
                    }
                },
                {
                    "node": {
                        "__typename": "ReferencedEvent"
                    }
                },
                {
                    "node": {
                        "__typename": "MergedEvent"
                    }
                },
                {
                    "node": {
                        "__typename": "HeadRefDeletedEvent"
                    }
                }
            ]
        },
        "number": 52,
        "createdAt": "2020-03-14T07:28:20Z",
        "title": "Bump acorn from 6.1.1 to 6.4.1 in /packages/eslint-config-react-native-community",
        "bodyText": "⚠️  Dependabot is rebasing this PR ⚠️\nIf you make any changes to it yourself then they will take precedence over the rebase.\n\nBumps acorn from 6.1.1 to 6.4.1.\n\nCommits\n\n9a2e9b6 Mark version 6.4.1\n90a9548 More rigorously check surrogate pairs in regexp validator\ndf0cf1a Mark version 6.4.0\n5303412 Also export Parser via Parser.acorn\nefe273e give token types and etc to plugins\nac6decb Mark version 6.3.0\n7e9817d Allow sourceType: module even with ecmaVersion < 6\ne2b8cc0 Fix broken parsing of new expressions when allowReserved==\"never\"\n1555c52 Update acorn.d.ts\n77c20fa Mark version 6.2.1\nAdditional commits viewable in compare view\n\n\n\n\nDependabot will resolve any conflicts with this PR as long as you don't alter it yourself. You can also trigger a rebase manually by commenting @dependabot rebase.\n\n\nDependabot commands and options\n\nYou can trigger Dependabot actions by commenting on this PR:\n\n@dependabot rebase will rebase this PR\n@dependabot recreate will recreate this PR, overwriting any edits that have been made to it\n@dependabot merge will merge this PR after your CI passes on it\n@dependabot squash and merge will squash and merge this PR after your CI passes on it\n@dependabot cancel merge will cancel a previously requested merge and block automerging\n@dependabot reopen will reopen this PR if it is closed\n@dependabot close will close this PR and stop Dependabot recreating it. You can achieve the same result by closing it manually\n@dependabot ignore this major version will close this PR and stop Dependabot creating any more for this major version (unless you reopen the PR or upgrade to it yourself)\n@dependabot ignore this minor version will close this PR and stop Dependabot creating any more for this minor version (unless you reopen the PR or upgrade to it yourself)\n@dependabot ignore this dependency will close this PR and stop Dependabot creating any more for this dependency (unless you reopen the PR or upgrade to it yourself)\n@dependabot use these labels will set the current labels as the default for future PRs for this repo and language\n@dependabot use these reviewers will set the current reviewers as the default for future PRs for this repo and language\n@dependabot use these assignees will set the current assignees as the default for future PRs for this repo and language\n@dependabot use this milestone will set the current milestone as the default for future PRs for this repo and language\n\nYou can disable automated security fix PRs for this repo from the Security Alerts page.",
        "state": "MERGED",
        "closed": true,
        "merged": true,
        "closedAt": "2020-04-06T18:13:54Z",
        "mergedBy": {
            "login": "dlowder-salesforce",
            "resourcePath": "/dlowder-salesforce"
        },
        "comments": {
            "nodes": []
        },
        "files": {
            "nodes": [
                {
                    "path": "packages/eslint-config-react-native-community/yarn.lock"
                }
            ]
        }
    },
    {
        "timeline": {
            "edges": [
                {
                    "node": {
                        "__typename": "Commit"
                    }
                },
                {
                    "node": {
                        "__typename": "LabeledEvent"
                    }
                },
                {
                    "node": {
                        "__typename": "PullRequestReview"
                    }
                },
                {
                    "node": {
                        "__typename": "ReferencedEvent"
                    }
                },
                {
                    "node": {
                        "__typename": "MergedEvent"
                    }
                },
                {
                    "node": {
                        "__typename": "HeadRefDeletedEvent"
                    }
                }
            ]
        },
        "number": 53,
        "createdAt": "2020-03-14T07:34:45Z",
        "title": "Bump acorn from 5.7.3 to 5.7.4",
        "bodyText": "Bumps acorn from 5.7.3 to 5.7.4.\n\nCommits\n\n6370e90 Mark version 5.7.4\nfbc15b1 More rigorously check surrogate pairs in regexp validator\nSee full diff in compare view\n\n\n\n\nDependabot will resolve any conflicts with this PR as long as you don't alter it yourself. You can also trigger a rebase manually by commenting @dependabot rebase.\n\n\nDependabot commands and options\n\nYou can trigger Dependabot actions by commenting on this PR:\n\n@dependabot rebase will rebase this PR\n@dependabot recreate will recreate this PR, overwriting any edits that have been made to it\n@dependabot merge will merge this PR after your CI passes on it\n@dependabot squash and merge will squash and merge this PR after your CI passes on it\n@dependabot cancel merge will cancel a previously requested merge and block automerging\n@dependabot reopen will reopen this PR if it is closed\n@dependabot close will close this PR and stop Dependabot recreating it. You can achieve the same result by closing it manually\n@dependabot ignore this major version will close this PR and stop Dependabot creating any more for this major version (unless you reopen the PR or upgrade to it yourself)\n@dependabot ignore this minor version will close this PR and stop Dependabot creating any more for this minor version (unless you reopen the PR or upgrade to it yourself)\n@dependabot ignore this dependency will close this PR and stop Dependabot creating any more for this dependency (unless you reopen the PR or upgrade to it yourself)\n@dependabot use these labels will set the current labels as the default for future PRs for this repo and language\n@dependabot use these reviewers will set the current reviewers as the default for future PRs for this repo and language\n@dependabot use these assignees will set the current assignees as the default for future PRs for this repo and language\n@dependabot use this milestone will set the current milestone as the default for future PRs for this repo and language\n\nYou can disable automated security fix PRs for this repo from the Security Alerts page.",
        "state": "MERGED",
        "closed": true,
        "merged": true,
        "closedAt": "2020-04-06T18:13:14Z",
        "mergedBy": {
            "login": "dlowder-salesforce",
            "resourcePath": "/dlowder-salesforce"
        },
        "comments": {
            "nodes": []
        },
        "files": {
            "nodes": [
                {
                    "path": "yarn.lock"
                }
            ]
        }
    },
    {
        "timeline": {
            "edges": [
                {
                    "node": {
                        "__typename": "Commit"
                    }
                },
                {
                    "node": {
                        "__typename": "ReviewRequestedEvent"
                    }
                },
                {
                    "node": {
                        "__typename": "LabeledEvent"
                    }
                },
                {
                    "node": {
                        "__typename": "PullRequestReview"
                    }
                },
                {
                    "node": {
                        "__typename": "ReferencedEvent"
                    }
                },
                {
                    "node": {
                        "__typename": "MergedEvent"
                    }
                },
                {
                    "node": {
                        "__typename": "HeadRefDeletedEvent"
                    }
                }
            ]
        },
        "number": 54,
        "createdAt": "2020-03-16T05:43:16Z",
        "title": "Bump minimist from 1.2.0 to 1.2.5 in /bots",
        "bodyText": "Bumps minimist from 1.2.0 to 1.2.5.\n\nCommits\n\naeb3e27 1.2.5\n278677b 1.2.4\n4cf1354 security notice\n1043d21 additional test for constructor prototype pollution\n6457d74 1.2.3\n38a4d1c even more aggressive checks for protocol pollution\n13c01a5 more failing proto pollution tests\nf34df07 1.2.2\n67d3722 cleanup\n63e7ed0 don't assign onto proto\nAdditional commits viewable in compare view\n\n\n\n\nDependabot will resolve any conflicts with this PR as long as you don't alter it yourself. You can also trigger a rebase manually by commenting @dependabot rebase.\n\n\nDependabot commands and options\n\nYou can trigger Dependabot actions by commenting on this PR:\n\n@dependabot rebase will rebase this PR\n@dependabot recreate will recreate this PR, overwriting any edits that have been made to it\n@dependabot merge will merge this PR after your CI passes on it\n@dependabot squash and merge will squash and merge this PR after your CI passes on it\n@dependabot cancel merge will cancel a previously requested merge and block automerging\n@dependabot reopen will reopen this PR if it is closed\n@dependabot close will close this PR and stop Dependabot recreating it. You can achieve the same result by closing it manually\n@dependabot ignore this major version will close this PR and stop Dependabot creating any more for this major version (unless you reopen the PR or upgrade to it yourself)\n@dependabot ignore this minor version will close this PR and stop Dependabot creating any more for this minor version (unless you reopen the PR or upgrade to it yourself)\n@dependabot ignore this dependency will close this PR and stop Dependabot creating any more for this dependency (unless you reopen the PR or upgrade to it yourself)\n@dependabot use these labels will set the current labels as the default for future PRs for this repo and language\n@dependabot use these reviewers will set the current reviewers as the default for future PRs for this repo and language\n@dependabot use these assignees will set the current assignees as the default for future PRs for this repo and language\n@dependabot use this milestone will set the current milestone as the default for future PRs for this repo and language\n\nYou can disable automated security fix PRs for this repo from the Security Alerts page.",
        "state": "MERGED",
        "closed": true,
        "merged": true,
        "closedAt": "2020-04-06T18:12:29Z",
        "mergedBy": {
            "login": "dlowder-salesforce",
            "resourcePath": "/dlowder-salesforce"
        },
        "comments": {
            "nodes": []
        },
        "files": {
            "nodes": [
                {
                    "path": "bots/yarn.lock"
                }
            ]
        }
    },
    {
        "timeline": {
            "edges": [
                {
                    "node": {
                        "__typename": "Commit"
                    }
                },
                {
                    "node": {
                        "__typename": "ReviewRequestedEvent"
                    }
                },
                {
                    "node": {
                        "__typename": "LabeledEvent"
                    }
                },
                {
                    "node": {
                        "__typename": "PullRequestReview"
                    }
                },
                {
                    "node": {
                        "__typename": "ReferencedEvent"
                    }
                },
                {
                    "node": {
                        "__typename": "MergedEvent"
                    }
                },
                {
                    "node": {
                        "__typename": "HeadRefDeletedEvent"
                    }
                }
            ]
        },
        "number": 64,
        "createdAt": "2020-04-16T12:30:16Z",
        "title": "Bump https-proxy-agent from 2.2.1 to 2.2.4 in /bots",
        "bodyText": "Bumps https-proxy-agent from 2.2.1 to 2.2.4.\n\nRelease notes\nSourced from https-proxy-agent's releases.\n\n2.2.4\nPatches\n\nAdd .editorconfig file: a0d4a20458498fc31e5721471bd2b655e992d44b\nAdd .eslintrc.js file: eecea74a1db1c943eaa4f667a561fd47c33da897\nUse a net.Socket instead of a plain EventEmitter for replaying proxy errors: #83\nRemove unused stream module: 9fdcd47bd813e9979ee57920c69e2ee2e0683cd4\n\nCredits\nHuge thanks to @lpinca for helping!\n2.2.3\nPatches\n\nUpdate README with actual secureProxy behavior: #65\nUpdate proxy to v1.0.0: d0e3c18079119057b05582cb72d4fda21dfc2546\nRemove unreachable code: 46aad0988b471f042856436cf3192b0e09e36fe6\nTest on Node.js 10 and 12: 3535951e482ea52af4888938f59649ed92e81b2b\nFix compatibility with Node.js >= 10.0.0: #73\nUse an EventEmitter to replay failed proxy connect HTTP requests: #77\n\nCredits\nHuge thanks to @stoically, @lpinca, and @zkochan for helping!\n2.2.2\nPatches\n\nRemove package-lock.json: c881009b9873707f5c4a0e9c277dde588e1139c7\nIgnore test directory, History.md and .travis.yml when creating npm package. Fixes #42: #45\nUpdate agent-base to v4.2: #50\nAdd TypeScript type definitions: #66\nFeat(typescript): Allow input to be options or string: #68\nUpdate agent-base to v4.3: #69\n\nCredits\nHuge thanks to @marco-c, @tareqhs, @ianhowe76, and @BYK for helping!\n\n\n\nCommits\n\n4c4cce8 2.2.4\n9fdcd47 Remove unused stream module\n34ea884 Use a net.Socket instead of a plain EventEmitter for replaying proxy erro...\n4296770 Prettier\neecea74 Add .eslintrc.js file\na0d4a20 Add .editorconfig file\n0d8e8bf 2.2.3\n850b835 Revert \"Use Mocha 5 for Node 4 support\"\nf5f56fa Remove Node 4 from Travis\nbb837b9 Revert \"Remove Node 4 from Travis\"\nAdditional commits viewable in compare view\n\n\n\n\nDependabot will resolve any conflicts with this PR as long as you don't alter it yourself. You can also trigger a rebase manually by commenting @dependabot rebase.\n\n\nDependabot commands and options\n\nYou can trigger Dependabot actions by commenting on this PR:\n\n@dependabot rebase will rebase this PR\n@dependabot recreate will recreate this PR, overwriting any edits that have been made to it\n@dependabot merge will merge this PR after your CI passes on it\n@dependabot squash and merge will squash and merge this PR after your CI passes on it\n@dependabot cancel merge will cancel a previously requested merge and block automerging\n@dependabot reopen will reopen this PR if it is closed\n@dependabot close will close this PR and stop Dependabot recreating it. You can achieve the same result by closing it manually\n@dependabot ignore this major version will close this PR and stop Dependabot creating any more for this major version (unless you reopen the PR or upgrade to it yourself)\n@dependabot ignore this minor version will close this PR and stop Dependabot creating any more for this minor version (unless you reopen the PR or upgrade to it yourself)\n@dependabot ignore this dependency will close this PR and stop Dependabot creating any more for this dependency (unless you reopen the PR or upgrade to it yourself)\n@dependabot use these labels will set the current labels as the default for future PRs for this repo and language\n@dependabot use these reviewers will set the current reviewers as the default for future PRs for this repo and language\n@dependabot use these assignees will set the current assignees as the default for future PRs for this repo and language\n@dependabot use this milestone will set the current milestone as the default for future PRs for this repo and language\n\nYou can disable automated security fix PRs for this repo from the Security Alerts page.",
        "state": "MERGED",
        "closed": true,
        "merged": true,
        "closedAt": "2020-05-26T17:01:14Z",
        "mergedBy": {
            "login": "dlowder-salesforce",
            "resourcePath": "/dlowder-salesforce"
        },
        "comments": {
            "nodes": []
        },
        "files": {
            "nodes": [
                {
                    "path": "bots/yarn.lock"
                }
            ]
        }
    }
]